text2html/__init__.py
text2html/page.py
text2html/sohtml.py
text2html-0.0.2.dev0.dist-info/DESCRIPTION.rst
text2html-0.0.2.dev0.dist-info/METADATA
text2html-0.0.2.dev0.dist-info/RECORD
text2html-0.0.2.dev0.dist-info/WHEEL
text2html-0.0.2.dev0.dist-info/entry_points.txt
text2html-0.0.2.dev0.dist-info/metadata.json
text2html-0.0.2.dev0.dist-info/top_level.txt
