Metadata-Version: 2.0
Name: text2html
Version: 0.0.2.dev0
Summary: create HTML files from some text files
Home-page: UNKNOWN
Author: solima
Author-email: UNKNOWN
License: GPL
Keywords: HTML text file create
Platform: UNKNOWN
